twmap-0.6.6.dist-info/METADATA
twmap-0.6.6.dist-info/WHEEL
twmap/__init__.py
twmap/__init__.pyi
twmap/py.typed
twmap/twmap.pypy311-pp73-darwin.so
twmap-0.6.6.dist-info/RECORD
