Metadata-Version: 2.4
Name: twmap
Version: 0.6.6
Summary: Python bindings for the crate twmap
Author: Patiga <dev@patiga.eu>
Author-email: Patiga <dev@patiga.eu>
License: AGPL-3.0-only
Project-URL: Source Code, https://gitlab.com/Patiga/twmap-py
